[
    {
        "questionStem": "1964年底，周恩来在三届全国人大一次会议上所作的政府工作报告中正式宣布，“把我国建设成为一个具有____、____、____的社会主义强国”。",
        "option": "",
        "answer": "现代农业，现代工业，现代国防和现代科学技术",
        "id": "1796422171472429056",
        "likeFlag": false,
        "markFlag": false,
        "abbreviationSubject": "CCPH"
    },
    {
        "questionStem": "毛泽东强调，____是社会主义国家政治生活的主题。",
        "option": "",
        "answer": "关于正确处理人民内部矛盾的问题",
        "id": "1796422171317239808",
        "likeFlag": false,
        "markFlag": false,
        "abbreviationSubject": "CCPH"
    },
    {
        "questionStem": "____是党执政兴国的第一要务。",
        "option": "",
        "answer": "发展",
        "id": "1796422173066264576",
        "likeFlag": false,
        "markFlag": false,
        "abbreviationSubject": "CCPH"
    },
    {
        "questionStem": "党的十八大以来，中国特色社会主义进入____，这是我国发展新的历史方位。",
        "option": "",
        "answer": "新时代",
        "id": "1796422173993205760",
        "likeFlag": false,
        "markFlag": false,
        "abbreviationSubject": "CCPH"
    },
    {
        "questionStem": "____是我国改革开放和社会主义现代化建设的总设计师。",
        "option": "",
        "answer": "邓小平",
        "id": "1796422172760080384",
        "likeFlag": false,
        "markFlag": false,
        "abbreviationSubject": "CCPH"
    },
    {
        "questionStem": "毛泽东思想的活的灵魂，是贯串于上述各个组成部分的立场、观点和方法，它们有三个基本方面，即____、____、____。",
        "option": "",
        "answer": "实事求是，群众路线，独立自主",
        "id": "1796422170033782784",
        "likeFlag": false,
        "markFlag": false,
        "abbreviationSubject": "CCPH"
    },
    {
        "questionStem": "1978年12月召开的党的十一届三中全会，作出实行____的重大决策。",
        "option": "",
        "answer": "改革开放",
        "id": "1796422171782807552",
        "likeFlag": false,
        "markFlag": false,
        "abbreviationSubject": "CCPH"
    },
    {
        "questionStem": "中国共产党的最早组织是在____建立的。",
        "option": "",
        "answer": "上海",
        "id": "1796422169673072640",
        "likeFlag": false,
        "markFlag": false,
        "abbreviationSubject": "CCPH"
    },
    {
        "questionStem": "____是中国特色社会主义最本质的特征，是中国特色社会主义制度的最大优势。",
        "option": "",
        "answer": "中国共产党的领导",
        "id": "1796422174144200704",
        "likeFlag": false,
        "markFlag": false,
        "abbreviationSubject": "CCPH"
    },
    {
        "questionStem": "“自力更生，____”是实现奋斗目标的根本立足点。",
        "option": "",
        "answer": "艰苦创业",
        "id": "1796422172298706944",
        "likeFlag": false,
        "markFlag": false,
        "abbreviationSubject": "CCPH"
    },
    {
        "questionStem": "____是一个民族最根本的事业，要面向现代化，面向世界，面向未来。",
        "option": "",
        "answer": "教育",
        "id": "1796422172604891136",
        "likeFlag": false,
        "markFlag": false,
        "abbreviationSubject": "CCPH"
    },
    {
        "questionStem": "社会主义的根本任务是____，党和国家的工作重点是经济建设，这是党对我国社会主义建设经验教训和社会主要矛盾进行科学分析得出的最重要的结论。",
        "option": "",
        "answer": "发展生产力",
        "id": "1796422172504227840",
        "likeFlag": false,
        "markFlag": false,
        "abbreviationSubject": "CCPH"
    },
    {
        "questionStem": "1949年3月，党在河北平山县____召开七届二中全会。",
        "option": "",
        "answer": "西柏坡",
        "id": "1796422170499350528",
        "likeFlag": false,
        "markFlag": false,
        "abbreviationSubject": "CCPH"
    },
    {
        "questionStem": "____是中国革命最基本的动力。",
        "option": "",
        "answer": "无产阶级",
        "id": "1796422170600013824",
        "likeFlag": false,
        "markFlag": false,
        "abbreviationSubject": "CCPH"
    },
    {
        "questionStem": "____是社会主义社会发展的直接动力。",
        "option": "",
        "answer": "改革",
        "id": "1796422172655222784",
        "likeFlag": false,
        "markFlag": false,
        "abbreviationSubject": "CCPH"
    },
    {
        "questionStem": "毛泽东思想是____的第一个重大理论成果。",
        "option": "",
        "answer": "马克思主义中国化时代化",
        "id": "1796422170344161280",
        "likeFlag": false,
        "markFlag": false,
        "abbreviationSubject": "CCPH"
    },
    {
        "questionStem": "____标志着党探索中国社会主义建设道路的良好开端。",
        "option": "",
        "answer": "《论十大关系》",
        "id": "1796422171216576512",
        "likeFlag": false,
        "markFlag": false,
        "abbreviationSubject": "CCPH"
    },
    {
        "questionStem": "1978年12月召开的党的十一届三中全会，重新确立了____的思想路线。",
        "option": "",
        "answer": "实事求是",
        "id": "1796422171732475904",
        "likeFlag": false,
        "markFlag": false,
        "abbreviationSubject": "CCPH"
    },
    {
        "questionStem": "党的____是党的全部工作和战斗力的基础。",
        "option": "",
        "answer": "基层组织",
        "id": "1796422173271785472",
        "likeFlag": false,
        "markFlag": false,
        "abbreviationSubject": "CCPH"
    },
    {
        "questionStem": "____是第一生产力，是先进生产力的集中体现和主要标志。",
        "option": "",
        "answer": "科学技术",
        "id": "1796422172915269632",
        "likeFlag": false,
        "markFlag": false,
        "abbreviationSubject": "CCPH"
    },
    {
        "questionStem": "1920年8月，上海共产党组织正式成立，____任书记。",
        "option": "",
        "answer": "陈独秀",
        "id": "1796422169983451136",
        "likeFlag": false,
        "markFlag": false,
        "abbreviationSubject": "CCPH"
    },
    {
        "questionStem": "发展先进文化，必须坚持____在意识形态领域的指导地位",
        "option": "",
        "answer": "马克思主义",
        "id": "1796422172965601280",
        "likeFlag": false,
        "markFlag": false,
        "abbreviationSubject": "CCPH"
    },
    {
        "questionStem": "____是兴国之魂。",
        "option": "",
        "answer": "社会主义核心价值体系",
        "id": "1796422173888348160",
        "likeFlag": false,
        "markFlag": false,
        "abbreviationSubject": "CCPH"
    },
    {
        "questionStem": "____是共产党人精神上的“钙”，共产党人如果没有理想信念，精神上就会“缺钙”，就会得“软骨病”",
        "option": "",
        "answer": "理想信念",
        "id": "1796422174299389952",
        "likeFlag": false,
        "markFlag": false,
        "abbreviationSubject": "CCPH"
    },
    {
        "questionStem": "____、____，是邓小平理论的精髓。",
        "option": "",
        "answer": "解放思想，实事求是",
        "id": "1796422171988328448",
        "likeFlag": false,
        "markFlag": false,
        "abbreviationSubject": "CCPH"
    },
    {
        "questionStem": "____，标志着新民主主义革命的伟大开端。",
        "option": "",
        "answer": "五四运动",
        "id": "1796422169442385920",
        "likeFlag": false,
        "markFlag": false,
        "abbreviationSubject": "CCPH"
    },
    {
        "questionStem": "“____”回答了解放和发展生产力的政治保证问题。",
        "option": "",
        "answer": "坚持四项基本原则",
        "id": "1796422172088991744",
        "likeFlag": false,
        "markFlag": false,
        "abbreviationSubject": "CCPH"
    },
    {
        "questionStem": "____是我们党打响武装反抗国民党反动派的第一枪。",
        "option": "",
        "answer": "南昌起义",
        "id": "1796422169559826432",
        "likeFlag": false,
        "markFlag": false,
        "abbreviationSubject": "CCPH"
    },
    {
        "questionStem": "____是科学发展观的根本方法。",
        "option": "",
        "answer": "统筹兼顾",
        "id": "1796422173577969664",
        "likeFlag": false,
        "markFlag": false,
        "abbreviationSubject": "CCPH"
    },
    {
        "questionStem": "____运动推动了中国社会的思想启蒙。",
        "option": "",
        "answer": "新文化",
        "id": "1796422169727598592",
        "likeFlag": false,
        "markFlag": false,
        "abbreviationSubject": "CCPH"
    },
    {
        "questionStem": "全面深化改革总目标是完善和发展____、推进国家治理体系和治理能力现代化。",
        "option": "",
        "answer": "中国特色社会主义制度",
        "id": "1796422174194532352",
        "likeFlag": false,
        "markFlag": false,
        "abbreviationSubject": "CCPH"
    },
    {
        "questionStem": "农业社会主义改造大体上经历了互助组、____和____三个发展阶段。",
        "option": "",
        "answer": "初级社，高级社",
        "id": "1796422171111718912",
        "likeFlag": false,
        "markFlag": false,
        "abbreviationSubject": "CCPH"
    },
    {
        "questionStem": "社会主义最大的优越性就是____，这是体现社会主义本质的一个东西。",
        "option": "",
        "answer": "共同富裕",
        "id": "1796422171937996800",
        "likeFlag": false,
        "markFlag": false,
        "abbreviationSubject": "CCPH"
    },
    {
        "questionStem": "____的成功，标志着第一次国共合作正式形成。",
        "option": "",
        "answer": "国民党一大",
        "id": "1796422170188972032",
        "likeFlag": false,
        "markFlag": false,
        "abbreviationSubject": "CCPH"
    },
    {
        "questionStem": "坚持中国共产党的领导，核心是坚持党的____。",
        "option": "",
        "answer": "先进性",
        "id": "1796422173116596224",
        "likeFlag": false,
        "markFlag": false,
        "abbreviationSubject": "CCPH"
    },
    {
        "questionStem": "____是中国特色社会主义事业的领导核心。",
        "option": "",
        "answer": "中国共产党",
        "id": "1796422172244180992",
        "likeFlag": false,
        "markFlag": false,
        "abbreviationSubject": "CCPH"
    },
    {
        "questionStem": "周恩来提出了____中的绝大部分是工人阶级一部分的观点。",
        "option": "",
        "answer": "知识分子",
        "id": "1796422171522760704",
        "likeFlag": false,
        "markFlag": false,
        "abbreviationSubject": "CCPH"
    },
    {
        "questionStem": "____是科学发展观的基本要求。",
        "option": "",
        "answer": "全面协调可持续",
        "id": "1796422173527638016",
        "likeFlag": false,
        "markFlag": false,
        "abbreviationSubject": "CCPH"
    },
    {
        "questionStem": "对于政治思想领域的人民内部矛盾，实行“团结一批评—团结”的方针，坚持____、____的方法；",
        "option": "",
        "answer": "说服教育，讨论",
        "id": "1796422171266908160",
        "likeFlag": false,
        "markFlag": false,
        "abbreviationSubject": "CCPH"
    },
    {
        "questionStem": "出席一大的上海代表是____和____。",
        "option": "",
        "answer": "李达，李汉俊",
        "id": "1796422170088308736",
        "likeFlag": false,
        "markFlag": false,
        "abbreviationSubject": "CCPH"
    },
    {
        "questionStem": "遵循自愿互利、____和国家帮助的原则，以互助合作的优越性吸引农民走互助合作道路。",
        "option": "",
        "answer": "典型示范",
        "id": "1796422171061387264",
        "likeFlag": false,
        "markFlag": false,
        "abbreviationSubject": "CCPH"
    },
    {
        "questionStem": "坚持科学发展，必须加快转变____。",
        "option": "",
        "answer": "经济发展方式",
        "id": "1796422173376643072",
        "likeFlag": false,
        "markFlag": false,
        "abbreviationSubject": "CCPH"
    },
    {
        "questionStem": "2017年，党的十九大把____确立为党必须长期坚持的指导思想并庄严地写入党章，实现了党的指导思想的与时俱进。",
        "option": "",
        "answer": "习近平新时代中国特色社会主义思想",
        "id": "1796422174043537408",
        "likeFlag": false,
        "markFlag": false,
        "abbreviationSubject": "CCPH"
    },
    {
        "questionStem": "党的七届二中全会提出了使中国“稳步地由农业国转变为工业国，____即“两个转变”同时并举的思想。",
        "option": "",
        "answer": "由新民主主义国家转变为社会主义国家",
        "id": "1796422170906198016",
        "likeFlag": false,
        "markFlag": false,
        "abbreviationSubject": "CCPH"
    },
    {
        "questionStem": "实践证明，____是当代中国的鲜明标志和活力源泉，是决定中国命运的关键一招，也是实现中华民族伟大复兴的关键一招。",
        "option": "",
        "answer": "改革开放",
        "id": "1796422172709748736",
        "likeFlag": false,
        "markFlag": false,
        "abbreviationSubject": "CCPH"
    },
    {
        "questionStem": "坚持和发展马克思主义，必须同____相结合、同____相结合。",
        "option": "",
        "answer": "中国具体实际，中华优秀传统文化",
        "id": "1796422174504910848",
        "likeFlag": false,
        "markFlag": false,
        "abbreviationSubject": "CCPH"
    },
    {
        "questionStem": "党的十八大指出：建设中国特色社会主义，总依据是____，总布局是五位一体，总任务是实现社会主义现代化和中华民族伟大复兴。",
        "option": "",
        "answer": "社会主义初级阶段",
        "id": "1796422174093869056",
        "likeFlag": false,
        "markFlag": false,
        "abbreviationSubject": "CCPH"
    },
    {
        "questionStem": "在新民主主义社会中，存在着五种经济成分，即社会主义性质的国营经济、半社会主义性质的合作社经济、____、私人资本主义经济和国家资本主义经济。",
        "option": "",
        "answer": "农民和手工业者的个体经济",
        "id": "1796422170855866368",
        "likeFlag": false,
        "markFlag": false,
        "abbreviationSubject": "CCPH"
    },
    {
        "questionStem": "社会主义民主政治的本质和核心是____。",
        "option": "",
        "answer": "人民当家作主",
        "id": "1796422173733158912",
        "likeFlag": false,
        "markFlag": false,
        "abbreviationSubject": "CCPH"
    },
    {
        "questionStem": "____是中国有史以来最伟大的事件，也是二十世纪世界最伟大的事件之一。",
        "option": "",
        "answer": "农村革命根据地",
        "id": "1796422170755203072",
        "likeFlag": false,
        "markFlag": false,
        "abbreviationSubject": "CCPH"
    },
    {
        "questionStem": "____都是我们党的生命线和根本工作路线，是我们党永葆青春活力和战斗力的重要传家宝。",
        "option": "",
        "answer": "群众路线",
        "id": "1796422170293829632",
        "likeFlag": false,
        "markFlag": false,
        "abbreviationSubject": "CCPH"
    },
    {
        "questionStem": "____是科学发展观的核心立场。",
        "option": "",
        "answer": "以人为本",
        "id": "1796422173477306368",
        "likeFlag": false,
        "markFlag": false,
        "abbreviationSubject": "CCPH"
    },
    {
        "questionStem": "____是社会主义的生命，是我们党始终高扬的光辉旗帜。",
        "option": "",
        "answer": "人民民主",
        "id": "1796422173682827264",
        "likeFlag": false,
        "markFlag": false,
        "abbreviationSubject": "CCPH"
    },
    {
        "questionStem": "____标志着中国共产党在政治上走向成熟",
        "option": "",
        "answer": "遵义会议",
        "id": "1796422170394492928",
        "likeFlag": false,
        "markFlag": false,
        "abbreviationSubject": "CCPH"
    },
    {
        "questionStem": "____是中国革命的首要对象。",
        "option": "",
        "answer": "帝国主义",
        "id": "1796422170549682176",
        "likeFlag": false,
        "markFlag": false,
        "abbreviationSubject": "CCPH"
    },
    {
        "questionStem": "党在这个过渡时期的总路线和总任务，是要在一个相当长的时期内，逐步实现国家的社会主义工业化，并逐步实现国家对农业、____的社会主义改造。",
        "option": "",
        "answer": "对手工业和对资本主义工商业",
        "id": "1796422171011055616",
        "likeFlag": false,
        "markFlag": false,
        "abbreviationSubject": "CCPH"
    },
    {
        "questionStem": "____是中国革命的主力军。",
        "option": "",
        "answer": "农民",
        "id": "1796422170650345472",
        "likeFlag": false,
        "markFlag": false,
        "abbreviationSubject": "CCPH"
    },
    {
        "questionStem": "“____”回答了社会主义的根本任务问题。",
        "option": "",
        "answer": "以经济建设为中心",
        "id": "1796422172038660096",
        "likeFlag": false,
        "markFlag": false,
        "abbreviationSubject": "CCPH"
    },
    {
        "questionStem": "用____的方法改造资本主义工商业。",
        "option": "",
        "answer": "和平赎买",
        "id": "1796422171162050560",
        "likeFlag": false,
        "markFlag": false,
        "abbreviationSubject": "CCPH"
    },
    {
        "questionStem": "“贯彻‘三个代表’重要思想，关键在坚持与时俱进，核心在坚持____，本质在坚持执政为民。",
        "option": "",
        "answer": "党的先进性",
        "id": "1796422171883470848",
        "likeFlag": false,
        "markFlag": false,
        "abbreviationSubject": "CCPH"
    },
    {
        "questionStem": "____是经济社会发展中最活跃、最具革命性的因素，是先进生产力的集中体现和主要标志。",
        "option": "",
        "answer": "科学技术",
        "id": "1796422173426974720",
        "likeFlag": false,
        "markFlag": false,
        "abbreviationSubject": "CCPH"
    },
    {
        "questionStem": "____是科学发展观的第一要义。",
        "option": "",
        "answer": "推动经济社会发展",
        "id": "1796422173322117120",
        "likeFlag": false,
        "markFlag": false,
        "abbreviationSubject": "CCPH"
    },
    {
        "questionStem": "毛泽东指出，____、____和____，是中国共产党在中国革命中战胜敌人的三大法宝。",
        "option": "",
        "answer": "统一战线，武装斗争，党的建设",
        "id": "1796422169777930240",
        "likeFlag": false,
        "markFlag": false,
        "abbreviationSubject": "CCPH"
    },
    {
        "questionStem": "____是中国特色社会主义理论体系的开篇之作。",
        "option": "",
        "answer": "邓小平理论",
        "id": "1796422172810412032",
        "likeFlag": false,
        "markFlag": false,
        "abbreviationSubject": "CCPH"
    },
    {
        "questionStem": "“____”回答了社会主义的发展动力和外部条件问题。",
        "option": "",
        "answer": "坚持改革开放",
        "id": "1796422172193849344",
        "likeFlag": false,
        "markFlag": false,
        "abbreviationSubject": "CCPH"
    },
    {
        "questionStem": "邓小平明确指出“应当把____问题提到全人类的高度来认识、要从这个高度去观察问题和解决问题”",
        "option": "",
        "answer": "发展",
        "id": "1796422171627618304",
        "likeFlag": false,
        "markFlag": false,
        "abbreviationSubject": "CCPH"
    },
    {
        "questionStem": "中国产生了____，这是开天辟地的大事变。",
        "option": "",
        "answer": "共产党",
        "id": "1796422169501106176",
        "likeFlag": false,
        "markFlag": false,
        "abbreviationSubject": "CCPH"
    },
    {
        "questionStem": "____、敢于胜利，是党和人民不可战胜的强大精神力量。",
        "option": "",
        "answer": "敢于斗争",
        "id": "1796422174349721600",
        "likeFlag": false,
        "markFlag": false,
        "abbreviationSubject": "CCPH"
    },
    {
        "questionStem": "党的十九届六中全会指出，党确立习近平同志党中央的核心、____，确立____的指导地位，反映了全党全军全国各族人民共同心愿。",
        "option": "",
        "answer": "全党的核心地位，习近平新时代中国特色社会主义思想",
        "id": "1796422174349721602",
        "likeFlag": false,
        "markFlag": false,
        "abbreviationSubject": "CCPH"
    },
    {
        "questionStem": "力争到____ 年基本实现国防和军队现代化，到本世纪中叶把人民军队全面建成世界一流军队。",
        "option": "",
        "answer": "2035",
        "id": "1796422174349721601",
        "likeFlag": false,
        "markFlag": false,
        "abbreviationSubject": "CCPH"
    },
    {
        "questionStem": "当今时代，世界进入新的动荡变革期，世界百年未有之大变局和____相互交织、深度互动，中国同国际社会的联系空前紧密，中国对世界的依靠、对国际事务的参与在不断加深，世界对中国的依靠、对中国的影响也在不断加深。",
        "option": "",
        "answer": "中华民族伟大复兴战略全局",
        "id": "1796422174349721603",
        "likeFlag": false,
        "markFlag": false,
        "abbreviationSubject": "CCPH"
    },
    {
        "questionStem": "____和法治相互依存，相互作用，密不可分。法治当中有政治，没有脱离政治的法治。",
        "option": "",
        "answer": "政治",
        "id": "1796422174349721604",
        "likeFlag": false,
        "markFlag": false,
        "abbreviationSubject": "CCPH"
    },
    {
        "questionStem": "____是获得真知灼见的源头活水，是贯彻群众路线的有效途径。",
        "option": "",
        "answer": "调查研究",
        "id": "1796422174349721605",
        "likeFlag": false,
        "markFlag": false,
        "abbreviationSubject": "CCPH"
    },
    {
        "questionStem": "治理好我们这个大党和大国，必须坚持____特别是党中央集中统一领导，发扬党的自我革命精神，解决好大党独有难题。",
        "option": "",
        "answer": "党的全面领导",
        "id": "1796422174349721606",
        "likeFlag": false,
        "markFlag": false,
        "abbreviationSubject": "CCPH"
    },
    {
        "questionStem": "时代是出卷人，我们是答卷人，____是阅卷人。",
        "option": "",
        "answer": "人民",
        "id": "1796422174349721607",
        "likeFlag": false,
        "markFlag": false,
        "abbreviationSubject": "CCPH"
    },
    {
        "questionStem": "习近平强调“中国开放的大门只会____，永远____!”",
        "option": "",
        "answer": "越开越大，不会关上",
        "id": "1796422174349721608",
        "likeFlag": false,
        "markFlag": false,
        "abbreviationSubject": "CCPH"
    },
    {
        "questionStem": "中国特色社会主义有很多特点和特征，其中最本质的特征是____。这个最本质特征是在近代以来中国历史发展中形成的，是由中国最广大人民根本利益和实现中华民族伟大复兴历史任务决定的。",
        "option": "",
        "answer": "中国共产党领导",
        "id": "1796422174349721609",
        "likeFlag": false,
        "markFlag": false,
        "abbreviationSubject": "CCPH"
    },
    {
        "questionStem": "以习近平同志为核心的党中央团结带领全党全国各族人民砥砺前行，推动党和国家事业取得____、发生历史性变革，使中国特色社会主义展现出强大生命力。",
        "option": "",
        "answer": "历史性成就",
        "id": "1796422174349721610",
        "likeFlag": false,
        "markFlag": false,
        "abbreviationSubject": "CCPH"
    },
    {
        "questionStem": "____是中国特色社会主义最本质的特征，是社会主义法治最根本的保证。",
        "option": "",
        "answer": "党的领导",
        "id": "1796422174349721611",
        "likeFlag": false,
        "markFlag": false,
        "abbreviationSubject": "CCPH"
    },
    {
        "questionStem": "“天地与我并生，而万物与我为一”的“____”思想是中华文明的鲜明特色和独特标识，代表着我们祖先对处理人与自然关系的重要认识。",
        "option": "",
        "answer": "天人合一",
        "id": "1796422174349721612",
        "likeFlag": false,
        "markFlag": false,
        "abbreviationSubject": "CCPH"
    },
    {
        "questionStem": "以习近平同志为核心的党中央提出使____在资源配置中起决定性作用，更好发挥____作用，这是我们党在理论和实践上的重大推进，是对中国特色社会主义建设规律认识的一个新突破。",
        "option": "",
        "answer": "市场，政府",
        "id": "1796422174349721613",
        "likeFlag": false,
        "markFlag": false,
        "abbreviationSubject": "CCPH"
    },
    {
        "questionStem": "习近平指出：“中国特色社会主义，既坚持了科学社会主义基本原则，又根据时代条件赋予其鲜明的____。”",
        "option": "",
        "answer": "中国特色",
        "id": "1796422174349721614",
        "likeFlag": false,
        "markFlag": false,
        "abbreviationSubject": "CCPH"
    },
    {
        "questionStem": "团结就是力量，奋斗开创未来。____是中国共产党和中国人民最显著的精神标识，是中国人民创造历史伟业的必由之路。",
        "option": "",
        "answer": "团结奋斗",
        "id": "1796422174349721615",
        "likeFlag": false,
        "markFlag": false,
        "abbreviationSubject": "CCPH"
    },
    {
        "questionStem": "我国是工人阶级领导的、以工农联盟为基础的人民民主专政的社会主义国家，工人阶级领导是通过其先锋队——____实现的。",
        "option": "",
        "answer": "中国共产党领导",
        "id": "1796422174349721616",
        "likeFlag": false,
        "markFlag": false,
        "abbreviationSubject": "CCPH"
    },
    {
        "questionStem": "党的十八大以来，以习近平同志为核心的党中央团结带领全党全国各族人民,以坚如磐石的战略定力、开拓创新的进取精神,推进党和国家事业取得举世瞩目的伟大成就，开创了中国特色社会主义____，中国特色社会主义正成为21世纪科学社会主义发展的旗帜，成为振兴世界社会主义的中流砥柱。",
        "option": "",
        "answer": "新时代",
        "id": "1796422174349721617",
        "likeFlag": false,
        "markFlag": false,
        "abbreviationSubject": "CCPH"
    },
    {
        "questionStem": "党的十八大以来，中国特色社会主义进入新时代，以习近平同志为主要代表的中国共产党人，坚持把马克思主义基本原理同中国具体实际相结合、同____相结合，创立了习近平新时代中国特色社会主义思想，实现了马克思主义中国化时代化新的飞跃。",
        "option": "",
        "answer": "中华优秀传统文化",
        "id": "1796422174349721618",
        "likeFlag": false,
        "markFlag": false,
        "abbreviationSubject": "CCPH"
    },
    {
        "questionStem": "党的性质宗旨、理想信念、初心使命赋予中国特色社会主义事业以____、____、团结奋斗的力量，决定着中国特色社会主义事业的前途命运。",
        "option": "",
        "answer": "信仰的力量，真理的力量",
        "id": "1796422174349721619",
        "likeFlag": false,
        "markFlag": false,
        "abbreviationSubject": "CCPH"
    },
    {
        "questionStem": "____是灵魂，决定军队建设的政治方向。",
        "option": "",
        "answer": "听党指挥",
        "id": "1796422174349721620",
        "likeFlag": false,
        "markFlag": false,
        "abbreviationSubject": "CCPH"
    },
    {
        "questionStem": "秉持真实亲诚理念和____，加强同发展中国家团结合作。",
        "option": "",
        "answer": "正确义利观",
        "id": "1796422174349721621",
        "likeFlag": false,
        "markFlag": false,
        "abbreviationSubject": "CCPH"
    },
    {
        "questionStem": "党的____是党的根本性建设。",
        "option": "",
        "answer": "政治建设",
        "id": "",
        "likeFlag": false,
        "markFlag": false,
        "abbreviationSubject": "CCPH"
    },
    {
        "questionStem": "习近平指出：“实践证明，____是我们认识世界、把握规律、追求真理、改造世界的强大思想武器，是我们党和国家必须始终遵循的指导思想。”",
        "option": "",
        "answer": "马克思主义",
        "id": "1796422174349721622",
        "likeFlag": false,
        "markFlag": false,
        "abbreviationSubject": "CCPH"
    },
    {
        "questionStem": "坚持以____为中心，是新时代坚持和发展中国特色社会主义的根本立场。",
        "option": "",
        "answer": "人民",
        "id": "1796422174349721623",
        "likeFlag": false,
        "markFlag": false,
        "abbreviationSubject": "CCPH"
    },
    {
        "questionStem": "历史和实践充分证明，只有社会主义才能救中国，只有社会主义才能发展中国，只有坚持和发展____才能实现中华民族伟大复兴。",
        "option": "",
        "answer": "中国特色社会主义",
        "id": "1796422174349721624",
        "likeFlag": false,
        "markFlag": false,
        "abbreviationSubject": "CCPH"
    },
    {
        "questionStem": "____集中体现着全体人民共同的价值追求，是凝聚人心、汇聚民力的强大力量。",
        "option": "",
        "answer": "社会主义核心价值观",
        "id": "1796422174349721625",
        "likeFlag": false,
        "markFlag": false,
        "abbreviationSubject": "CCPH"
    },
    {
        "questionStem": "____是历史的创造者，是真正的英雄。",
        "option": "",
        "answer": "人民",
        "id": "1796422174349721626",
        "likeFlag": false,
        "markFlag": false,
        "abbreviationSubject": "CCPH"
    },
    {
        "questionStem": "中国式现代化，是中国共产党领导的社会主义现代化,既有各国现代化的共同特征，更有基于自己国情的____。",
        "option": "",
        "answer": "中国特色",
        "id": "1796422174349721627",
        "likeFlag": false,
        "markFlag": false,
        "abbreviationSubject": "CCPH"
    },
    {
        "questionStem": "建设教育强国的目的，就是要培养一代又一代____全面发展的社会主义建设者和接班人。",
        "option": "",
        "answer": "德智体美劳",
        "id": "1796422174349721628",
        "likeFlag": false,
        "markFlag": false,
        "abbreviationSubject": "CCPH"
    },
    {
        "questionStem": "习近平指出“开展调查研究就是走群众路线，没有调查就没有发言权，就没有____。”",
        "option": "",
        "answer": "决策权",
        "id": "1796422174349721629",
        "likeFlag": false,
        "markFlag": false,
        "abbreviationSubject": "CCPH"
    },
    {
        "questionStem": "我们党领导人们长期探索走出的____，是全面依法治国的唯一正确道路。这条道路是由我国社会主义国家性质所决定的，本质上是中国特色社会主义道路在法治领域的具体体现。",
        "option": "",
        "answer": "中国特色社会主义法治道路",
        "id": "1796422174349721630",
        "likeFlag": false,
        "markFlag": false,
        "abbreviationSubject": "CCPH"
    },
    {
        "questionStem": "____就是人民，人民就是____，这是由我们党的性质、宗旨决定的。",
        "option": "",
        "answer": "江山，江山",
        "id": "1796422174349721631",
        "likeFlag": false,
        "markFlag": false,
        "abbreviationSubject": "CCPH"
    }
]